{
    "stages": [
        {
            "stage_name": "stage01",
            "fps": 7200,
            "bgm_name": "stage01",
            "bgm_path": "notitle",
            "enemies": [
                {
                    "name": "",
                    "id": 1,
                    "type": 0,
                    "moveType": 1,
                    "lives": 1,
                    "hp": 10,
                    "radius": 12,
                    "shootType": 1,
                    "time": 0,
                    "spawnTime": 60,
                    "spellCount": 0,
                    "isAlive": 0,
                    "isSpell": 0,
                    "isInvincible": 0,
                    "invincibleTime": 0,
                    "pos": {
                        "x": 120.0,
                        "y": -32.0
                    },
                    "vel": {
                        "x": 0.0,
                        "y": 2.0
                    },
                    "spellAmount": 0
                },
                {
                    "name": "",
                    "id": 2,
                    "type": 0,
                    "moveType": 1,
                    "lives": 1,
                    "hp": 10,
                    "radius": 12,
                    "shootType": 1,
                    "time": 0,
                    "spawnTime": 90,
                    "spellCount": 0,
                    "isAlive": 0,
                    "isSpell": 0,
                    "isInvincible": 0,
                    "invincibleTime": 0,
                    "pos": {
                        "x": 320.0,
                        "y": -32.0
                    },
                    "vel": {
                        "x": 0.0,
                        "y": 2.0
                    }
                },
                {
                    "name": "",
                    "id": 3,
                    "type": 0,
                    "moveType": 1,
                    "lives": 1,
                    "hp": 10,
                    "radius": 12,
                    "shootType": 1,
                    "time": 0,
                    "spawnTime": 120,
                    "spellCount": 0,
                    "isAlive": 0,
                    "isSpell": 0,
                    "isInvincible": 0,
                    "invincibleTime": 0,
                    "pos": {
                        "x": 520.0,
                        "y": -32.0
                    },
                    "vel": {
                        "x": 0.0,
                        "y": 2.0
                    }
                },
                {
                    "name": "",
                    "id": 10,
                    "type": 0,
                    "moveType": 5,
                    "lives": 1,
                    "hp": 12,
                    "radius": 12,
                    "shootType": 5,
                    "time": 0,
                    "spawnTime": 360,
                    "spellCount": 0,
                    "isAlive": 0,
                    "isSpell": 0,
                    "isInvincible": 0,
                    "invincibleTime": 0,
                    "pos": {
                        "x": 100.0,
                        "y": -32.0
                    },
                    "vel": {
                        "x": 0.0,
                        "y": 2.0
                    }
                },
                {
                    "name": "",
                    "id": 11,
                    "type": 0,
                    "moveType": 5,
                    "lives": 1,
                    "hp": 12,
                    "radius": 12,
                    "shootType": 5,
                    "time": 0,
                    "spawnTime": 400,
                    "spellCount": 0,
                    "isAlive": 0,
                    "isSpell": 0,
                    "isInvincible": 0,
                    "invincibleTime": 0,
                    "pos": {
                        "x": 250.0,
                        "y": -32.0
                    },
                    "vel": {
                        "x": 0.0,
                        "y": 2.0
                    }
                },
                {
                    "name": "",
                    "id": 12,
                    "type": 0,
                    "moveType": 5,
                    "lives": 1,
                    "hp": 12,
                    "radius": 12,
                    "shootType": 5,
                    "time": 0,
                    "spawnTime": 440,
                    "spellCount": 0,
                    "isAlive": 0,
                    "isSpell": 0,
                    "isInvincible": 0,
                    "invincibleTime": 0,
                    "pos": {
                        "x": 400.0,
                        "y": -32.0
                    },
                    "vel": {
                        "x": 0.0,
                        "y": 2.0
                    }
                },
                {
                    "name": "",
                    "id": 13,
                    "type": 0,
                    "moveType": 5,
                    "lives": 1,
                    "hp": 12,
                    "radius": 12,
                    "shootType": 5,
                    "time": 0,
                    "spawnTime": 480,
                    "spellCount": 0,
                    "isAlive": 0,
                    "isSpell": 0,
                    "isInvincible": 0,
                    "invincibleTime": 0,
                    "pos": {
                        "x": 550.0,
                        "y": -32.0
                    },
                    "vel": {
                        "x": 0.0,
                        "y": 2.0
                    }
                },
                {
                    "name": "",
                    "id": 20,
                    "type": 0,
                    "moveType": 1,
                    "lives": 1,
                    "hp": 16,
                    "radius": 12,
                    "shootType": 2,
                    "time": 0,
                    "spawnTime": 900,
                    "spellCount": 0,
                    "isAlive": 0,
                    "isSpell": 0,
                    "isInvincible": 0,
                    "invincibleTime": 0,
                    "pos": {
                        "x": 160.0,
                        "y": -32.0
                    },
                    "vel": {
                        "x": 0.0,
                        "y": 2.0
                    },
                    "spellAmount": 0
                },
                {
                    "name": "",
                    "id": 21,
                    "type": 0,
                    "moveType": 1,
                    "lives": 1,
                    "hp": 16,
                    "radius": 12,
                    "shootType": 2,
                    "time": 0,
                    "spawnTime": 950,
                    "spellCount": 0,
                    "isAlive": 0,
                    "isSpell": 0,
                    "isInvincible": 0,
                    "invincibleTime": 0,
                    "pos": {
                        "x": 280.0,
                        "y": -32.0
                    },
                    "vel": {
                        "x": 0.0,
                        "y": 2.0
                    },
                    "spellAmount": 0
                },
                {
                    "name": "",
                    "id": 22,
                    "type": 0,
                    "moveType": 1,
                    "lives": 1,
                    "hp": 16,
                    "radius": 12,
                    "shootType": 2,
                    "time": 0,
                    "spawnTime": 1000,
                    "spellCount": 0,
                    "isAlive": 0,
                    "isSpell": 0,
                    "isInvincible": 0,
                    "invincibleTime": 0,
                    "pos": {
                        "x": 400.0,
                        "y": -32.0
                    },
                    "vel": {
                        "x": 0.0,
                        "y": 2.0
                    },
                    "spellAmount": 0
                },
                {
                    "name": "",
                    "id": 30,
                    "type": 0,
                    "moveType": 8,
                    "lives": 1,
                    "hp": 70,
                    "radius": 12,
                    "shootType": 6,
                    "time": 0,
                    "spawnTime": 1800,
                    "spellCount": 0,
                    "isAlive": 0,
                    "isSpell": 0,
                    "isInvincible": 0,
                    "invincibleTime": 0,
                    "pos": {
                        "x": 120.0,
                        "y": -32.0
                    },
                    "vel": {
                        "x": 0.0,
                        "y": 2.0
                    },
                    "spellAmount": 0
                },
                {
                    "name": "",
                    "id": 31,
                    "type": 0,
                    "moveType": 8,
                    "lives": 1,
                    "hp": 70,
                    "radius": 12,
                    "shootType": 6,
                    "time": 0,
                    "spawnTime": 1860,
                    "spellCount": 0,
                    "isAlive": 0,
                    "isSpell": 0,
                    "isInvincible": 0,
                    "invincibleTime": 0,
                    "pos": {
                        "x": 320.0,
                        "y": -32.0
                    },
                    "vel": {
                        "x": 0.0,
                        "y": 2.0
                    },
                    "spellAmount": 0
                },
                {
                    "name": "Boss",
                    "id": 100,
                    "type": 100,
                    "moveType": 4,
                    "lives": 3,
                    "hp": 500,
                    "radius": 28,
                    "shootType": 10,
                    "time": 0,
                    "spawnTime": 2700,
                    "spellCount": 0,
                    "isAlive": 0,
                    "isSpell": 0,
                    "isInvincible": 0,
                    "invincibleTime": 0,
                    "pos": {
                        "x": 320.0,
                        "y": -32.0
                    },
                    "vel": {
                        "x": 0.0,
                        "y": 2.0
                    },
                    "spellAmount": 3
                }
            ]
        },
        {
            "stage_name": "stage02",
            "fps": 3600,
            "bgm_name": "",
            "bgm_path": "",
            "enemies": [
                {
                    "name": "",
                    "id": 1,
                    "type": 0,
                    "moveType": 0,
                    "lives": 1,
                    "hp": 10,
                    "radius": 12,
                    "shootType": 5,
                    "time": 0,
                    "spawnTime": 60,
                    "spellCount": 0,
                    "spellAmount": 0,
                    "isAlive": 0,
                    "isSpell": 0,
                    "isInvincible": 0,
                    "invincibleTime": 0,
                    "pos": {
                        "x": 320.0,
                        "y": -32.0
                    },
                    "vel": {
                        "x": 0.0,
                        "y": 2.0
                    }
                },
                {
                    "name": "",
                    "id": 2,
                    "type": 0,
                    "moveType": 5,
                    "lives": 1,
                    "hp": 10,
                    "radius": 12,
                    "shootType": 1,
                    "time": 0,
                    "spawnTime": 65,
                    "spellCount": 0,
                    "spellAmount": 0,
                    "isAlive": 0,
                    "isSpell": 0,
                    "isInvincible": 0,
                    "invincibleTime": 0,
                    "pos": {
                        "x": 335.0,
                        "y": -32.0
                    },
                    "vel": {
                        "x": 0.0,
                        "y": 2.0
                    }
                },
                {
                    "name": "",
                    "id": 3,
                    "type": 0,
                    "moveType": 0,
                    "lives": 1,
                    "hp": 10,
                    "radius": 12,
                    "shootType": 5,
                    "time": 0,
                    "spawnTime": 70,
                    "spellCount": 0,
                    "spellAmount": 0,
                    "isAlive": 0,
                    "isSpell": 0,
                    "isInvincible": 0,
                    "invincibleTime": 0,
                    "pos": {
                        "x": 350.0,
                        "y": -32.0
                    },
                    "vel": {
                        "x": 0.0,
                        "y": 2.0
                    }
                },
                {
                    "name": "",
                    "id": 4,
                    "type": 0,
                    "moveType": 0,
                    "lives": 1,
                    "hp": 10,
                    "radius": 12,
                    "shootType": 5,
                    "time": 0,
                    "spawnTime": 75,
                    "spellCount": 0,
                    "spellAmount": 0,
                    "isAlive": 0,
                    "isSpell": 0,
                    "isInvincible": 0,
                    "invincibleTime": 0,
                    "pos": {
                        "x": 365.0,
                        "y": -32.0
                    },
                    "vel": {
                        "x": 0.0,
                        "y": 2.0
                    }
                },
                {
                    "name": "",
                    "id": 5,
                    "type": 0,
                    "moveType": 0,
                    "lives": 1,
                    "hp": 10,
                    "radius": 12,
                    "shootType": 5,
                    "time": 0,
                    "spawnTime": 80,
                    "spellCount": 0,
                    "spellAmount": 0,
                    "isAlive": 0,
                    "isSpell": 0,
                    "isInvincible": 0,
                    "invincibleTime": 0,
                    "pos": {
                        "x": 380.0,
                        "y": -32.0
                    },
                    "vel": {
                        "x": 0.0,
                        "y": 2.0
                    }
                },
                {
                    "name": "",
                    "id": 6,
                    "type": 0,
                    "moveType": 0,
                    "lives": 1,
                    "hp": 10,
                    "radius": 12,
                    "shootType": 5,
                    "time": 0,
                    "spawnTime": 85,
                    "spellCount": 0,
                    "spellAmount": 0,
                    "isAlive": 0,
                    "isSpell": 0,
                    "isInvincible": 0,
                    "invincibleTime": 0,
                    "pos": {
                        "x": 395.0,
                        "y": -32.0
                    },
                    "vel": {
                        "x": 0.0,
                        "y": 2.0
                    }
                },
                {
                    "name": "",
                    "id": 7,
                    "type": 0,
                    "moveType": 0,
                    "lives": 1,
                    "hp": 10,
                    "radius": 12,
                    "shootType": 5,
                    "time": 0,
                    "spawnTime": 90,
                    "spellCount": 0,
                    "spellAmount": 0,
                    "isAlive": 0,
                    "isSpell": 0,
                    "isInvincible": 0,
                    "invincibleTime": 0,
                    "pos": {
                        "x": 410.0,
                        "y": -32.0
                    },
                    "vel": {
                        "x": 0.0,
                        "y": 2.0
                    }
                },
                {
                    "name": "",
                    "id": 8,
                    "type": 0,
                    "moveType": 0,
                    "lives": 1,
                    "hp": 10,
                    "radius": 12,
                    "shootType": 5,
                    "time": 0,
                    "spawnTime": 95,
                    "spellCount": 0,
                    "spellAmount": 0,
                    "isAlive": 0,
                    "isSpell": 0,
                    "isInvincible": 0,
                    "invincibleTime": 0,
                    "pos": {
                        "x": 425.0,
                        "y": -32.0
                    },
                    "vel": {
                        "x": 0.0,
                        "y": 2.0
                    }
                },
                {
                    "name": "",
                    "id": 9,
                    "type": 0,
                    "moveType": 0,
                    "lives": 1,
                    "hp": 10,
                    "radius": 12,
                    "shootType": 5,
                    "time": 0,
                    "spawnTime": 100,
                    "spellCount": 0,
                    "spellAmount": 0,
                    "isAlive": 0,
                    "isSpell": 0,
                    "isInvincible": 0,
                    "invincibleTime": 0,
                    "pos": {
                        "x": 440.0,
                        "y": -32.0
                    },
                    "vel": {
                        "x": 0.0,
                        "y": 2.0
                    }
                },
                {
                    "name": "",
                    "id": 10,
                    "type": 0,
                    "moveType": 0,
                    "lives": 1,
                    "hp": 10,
                    "radius": 12,
                    "shootType": 5,
                    "time": 0,
                    "spawnTime": 105,
                    "spellCount": 0,
                    "spellAmount": 0,
                    "isAlive": 0,
                    "isSpell": 0,
                    "isInvincible": 0,
                    "invincibleTime": 0,
                    "pos": {
                        "x": 455.0,
                        "y": -32.0
                    },
                    "vel": {
                        "x": 0.0,
                        "y": 2.0
                    }
                },
                {
                    "name": "",
                    "id": 11,
                    "type": 0,
                    "moveType": 0,
                    "lives": 1,
                    "hp": 10,
                    "radius": 12,
                    "shootType": 5,
                    "time": 0,
                    "spawnTime": 110,
                    "spellCount": 0,
                    "spellAmount": 0,
                    "isAlive": 0,
                    "isSpell": 0,
                    "isInvincible": 0,
                    "invincibleTime": 0,
                    "pos": {
                        "x": 470.0,
                        "y": -32.0
                    },
                    "vel": {
                        "x": 0.0,
                        "y": 2.0
                    }
                },
                {
                    "name": "",
                    "id": 12,
                    "type": 0,
                    "moveType": 2,
                    "lives": 1,
                    "hp": 20,
                    "radius": 12,
                    "shootType": 1,
                    "time": 0,
                    "spawnTime": 300,
                    "spellCount": 0,
                    "spellAmount": 0,
                    "isAlive": 0,
                    "isSpell": 0,
                    "isInvincible": 0,
                    "invincibleTime": 0,
                    "pos": {
                        "x": 320.0,
                        "y": -32.0
                    },
                    "vel": {
                        "x": 0.0,
                        "y": 2.0
                    }
                },
                {
                    "name": "",
                    "id": 13,
                    "type": 0,
                    "moveType": 0,
                    "lives": 1,
                    "hp": 20,
                    "radius": 12,
                    "shootType": 1,
                    "time": 0,
                    "spawnTime": 360,
                    "spellCount": 0,
                    "spellAmount": 0,
                    "isAlive": 0,
                    "isSpell": 0,
                    "isInvincible": 0,
                    "invincibleTime": 0,
                    "pos": {
                        "x": 440.0,
                        "y": -32.0
                    },
                    "vel": {
                        "x": 0.0,
                        "y": 2.0
                    }
                },
                {
                    "name": "",
                    "id": 14,
                    "type": 0,
                    "moveType": 2,
                    "lives": 1,
                    "hp": 20,
                    "radius": 12,
                    "shootType": 1,
                    "time": 0,
                    "spawnTime": 420,
                    "spellCount": 0,
                    "spellAmount": 0,
                    "isAlive": 0,
                    "isSpell": 0,
                    "isInvincible": 0,
                    "invincibleTime": 0,
                    "pos": {
                        "x": 560.0,
                        "y": -32.0
                    },
                    "vel": {
                        "x": 0.0,
                        "y": 2.0
                    }
                },
                {
                    "name": "",
                    "id": 15,
                    "type": 0,
                    "moveType": 0,
                    "lives": 1,
                    "hp": 20,
                    "radius": 12,
                    "shootType": 1,
                    "time": 0,
                    "spawnTime": 480,
                    "spellCount": 0,
                    "spellAmount": 0,
                    "isAlive": 0,
                    "isSpell": 0,
                    "isInvincible": 0,
                    "invincibleTime": 0,
                    "pos": {
                        "x": 680.0,
                        "y": -32.0
                    },
                    "vel": {
                        "x": 0.0,
                        "y": 2.0
                    }
                },
                {
                    "name": "",
                    "id": 16,
                    "type": 0,
                    "moveType": 2,
                    "lives": 1,
                    "hp": 100,
                    "radius": 12,
                    "shootType": 1,
                    "time": 0,
                    "spawnTime": 900,
                    "spellCount": 0,
                    "spellAmount": 0,
                    "isAlive": 0,
                    "isSpell": 0,
                    "isInvincible": 0,
                    "invincibleTime": 0,
                    "pos": {
                        "x": 120.0,
                        "y": -32.0
                    },
                    "vel": {
                        "x": 0.0,
                        "y": 2.0
                    }
                },
                {
                    "name": "Boss",
                    "id": 101,
                    "type": 101,
                    "moveType": 4,
                    "lives": 4,
                    "hp": 800,
                    "radius": 28,
                    "shootType": 5,
                    "time": 0,
                    "spawnTime": 2700,
                    "spellCount": 0,
                    "spellAmount": 4,
                    "isAlive": 0,
                    "isSpell": 0,
                    "isInvincible": 0,
                    "invincibleTime": 0,
                    "pos": {
                        "x": 320.0,
                        "y": -32.0
                    },
                    "vel": {
                        "x": 0.0,
                        "y": 2.0
                    }
                },
                {
                    "name": "",
                    "id": 32,
                    "type": 0,
                    "moveType": 3,
                    "lives": 1,
                    "hp": 10,
                    "radius": 12,
                    "shootType": 1,
                    "time": 0,
                    "spawnTime": 1800,
                    "spellCount": 0,
                    "spellAmount": 0,
                    "isAlive": 0,
                    "isSpell": 0,
                    "isInvincible": 0,
                    "invincibleTime": 0,
                    "pos": {
                        "x": 320.0,
                        "y": -32.0
                    },
                    "vel": {
                        "x": 0.0,
                        "y": 2.0
                    }
                },
                {
                    "name": "",
                    "id": 33,
                    "type": 0,
                    "moveType": 3,
                    "lives": 1,
                    "hp": 10,
                    "radius": 12,
                    "shootType": 6,
                    "time": 0,
                    "spawnTime": 1860,
                    "spellCount": 0,
                    "spellAmount": 0,
                    "isAlive": 0,
                    "isSpell": 0,
                    "isInvincible": 0,
                    "invincibleTime": 0,
                    "pos": {
                        "x": 420.0,
                        "y": -32.0
                    },
                    "vel": {
                        "x": 0.0,
                        "y": 2.0
                    }
                },
                {
                    "name": "",
                    "id": 34,
                    "type": 0,
                    "moveType": 3,
                    "lives": 1,
                    "hp": 10,
                    "radius": 12,
                    "shootType": 6,
                    "time": 0,
                    "spawnTime": 1920,
                    "spellCount": 0,
                    "spellAmount": 0,
                    "isAlive": 0,
                    "isSpell": 0,
                    "isInvincible": 0,
                    "invincibleTime": 0,
                    "pos": {
                        "x": 520.0,
                        "y": -32.0
                    },
                    "vel": {
                        "x": 0.0,
                        "y": 2.0
                    }
                },
                {
                    "name": "",
                    "id": 35,
                    "type": 0,
                    "moveType": 3,
                    "lives": 1,
                    "hp": 10,
                    "radius": 12,
                    "shootType": 6,
                    "time": 0,
                    "spawnTime": 1980,
                    "spellCount": 0,
                    "spellAmount": 0,
                    "isAlive": 0,
                    "isSpell": 0,
                    "isInvincible": 0,
                    "invincibleTime": 0,
                    "pos": {
                        "x": 620.0,
                        "y": -32.0
                    },
                    "vel": {
                        "x": 0.0,
                        "y": 2.0
                    }
                },
                {
                    "name": "",
                    "id": 36,
                    "type": 0,
                    "moveType": 0,
                    "lives": 1,
                    "hp": 10,
                    "radius": 12,
                    "shootType": 1,
                    "time": 0,
                    "spawnTime": 60,
                    "spellCount": 0,
                    "spellAmount": 0,
                    "isAlive": 0,
                    "isSpell": 0,
                    "isInvincible": 0,
                    "invincibleTime": 0,
                    "pos": {
                        "x": 320.0,
                        "y": -32.0
                    },
                    "vel": {
                        "x": 0.0,
                        "y": 2.0
                    }
                },
                {
                    "name": "",
                    "id": 17,
                    "type": 0,
                    "moveType": 2,
                    "lives": 1,
                    "hp": 100,
                    "radius": 12,
                    "shootType": 1,
                    "time": 0,
                    "spawnTime": 1200,
                    "spellCount": 0,
                    "spellAmount": 0,
                    "isAlive": 0,
                    "isSpell": 0,
                    "isInvincible": 0,
                    "invincibleTime": 0,
                    "pos": {
                        "x": 60.0,
                        "y": -32.0
                    },
                    "vel": {
                        "x": 0.0,
                        "y": 2.0
                    }
                },
                {
                    "name": "",
                    "id": 18,
                    "type": 0,
                    "moveType": 2,
                    "lives": 1,
                    "hp": 100,
                    "radius": 12,
                    "shootType": 1,
                    "time": 0,
                    "spawnTime": 1500,
                    "spellCount": 0,
                    "spellAmount": 0,
                    "isAlive": 0,
                    "isSpell": 0,
                    "isInvincible": 0,
                    "invincibleTime": 0,
                    "pos": {
                        "x": 180.0,
                        "y": -32.0
                    },
                    "vel": {
                        "x": 0.0,
                        "y": 2.0
                    }
                },
                {
                    "name": "",
                    "id": 19,
                    "type": 0,
                    "moveType": 2,
                    "lives": 1,
                    "hp": 100,
                    "radius": 12,
                    "shootType": 1,
                    "time": 0,
                    "spawnTime": 1800,
                    "spellCount": 0,
                    "spellAmount": 0,
                    "isAlive": 0,
                    "isSpell": 0,
                    "isInvincible": 0,
                    "invincibleTime": 0,
                    "pos": {
                        "x": 240.0,
                        "y": -32.0
                    },
                    "vel": {
                        "x": 0.0,
                        "y": 2.0
                    }
                },
                {
                    "name": "",
                    "id": 20,
                    "type": 0,
                    "moveType": 2,
                    "lives": 1,
                    "hp": 100,
                    "radius": 12,
                    "shootType": 1,
                    "time": 0,
                    "spawnTime": 2100,
                    "spellCount": 0,
                    "spellAmount": 0,
                    "isAlive": 0,
                    "isSpell": 0,
                    "isInvincible": 0,
                    "invincibleTime": 0,
                    "pos": {
                        "x": 30.0,
                        "y": -32.0
                    },
                    "vel": {
                        "x": 0.0,
                        "y": 2.0
                    }
                },
                {
                    "name": "",
                    "id": 21,
                    "type": 0,
                    "moveType": 2,
                    "lives": 1,
                    "hp": 100,
                    "radius": 12,
                    "shootType": 1,
                    "time": 0,
                    "spawnTime": 2100,
                    "spellCount": 0,
                    "spellAmount": 0,
                    "isAlive": 0,
                    "isSpell": 0,
                    "isInvincible": 0,
                    "invincibleTime": 0,
                    "pos": {
                        "x": 510.0,
                        "y": -32.0
                    },
                    "vel": {
                        "x": 0.0,
                        "y": 2.0
                    }
                }
            ]
        },
        {
            "stage_name": "stage03",
            "fps": 60,
            "bgm_name": "notitle",
            "bgm_path": "./",
            "enemies": [
                {
                    "name": "",
                    "id": 1,
                    "type": 0,
                    "moveType": 0,
                    "lives": 1,
                    "hp": 20,
                    "radius": 12,
                    "shootType": 1,
                    "time": 10,
                    "spawnTime": 60,
                    "spellCount": 0,
                    "spellAmount": 0,
                    "isAlive": 0,
                    "isSpell": 0,
                    "isInvincible": 0,
                    "invincibleTime": 0,
                    "pos": {
                        "x": 60.0,
                        "y": -32.0
                    },
                    "vel": {
                        "x": 0.0,
                        "y": 2.0
                    }
                },
                {
                    "name": "",
                    "id": 2,
                    "type": 0,
                    "moveType": 0,
                    "lives": 1,
                    "hp": 20,
                    "radius": 12,
                    "shootType": 1,
                    "time": 10,
                    "spawnTime": 90,
                    "spellCount": 0,
                    "spellAmount": 0,
                    "isAlive": 0,
                    "isSpell": 0,
                    "isInvincible": 0,
                    "invincibleTime": 0,
                    "pos": {
                        "x": 90.0,
                        "y": -32.0
                    },
                    "vel": {
                        "x": 0.0,
                        "y": 2.0
                    }
                },
                {
                    "name": "",
                    "id": 3,
                    "type": 0,
                    "moveType": 0,
                    "lives": 1,
                    "hp": 20,
                    "radius": 12,
                    "shootType": 1,
                    "time": 10,
                    "spawnTime": 120,
                    "spellCount": 0,
                    "spellAmount": 0,
                    "isAlive": 0,
                    "isSpell": 0,
                    "isInvincible": 0,
                    "invincibleTime": 0,
                    "pos": {
                        "x": 120.0,
                        "y": -32.0
                    },
                    "vel": {
                        "x": 0.0,
                        "y": 2.0
                    }
                },
                {
                    "name": "",
                    "id": 4,
                    "type": 0,
                    "moveType": 0,
                    "lives": 1,
                    "hp": 20,
                    "radius": 12,
                    "shootType": 1,
                    "time": 10,
                    "spawnTime": 150,
                    "spellCount": 0,
                    "spellAmount": 0,
                    "isAlive": 0,
                    "isSpell": 0,
                    "isInvincible": 0,
                    "invincibleTime": 0,
                    "pos": {
                        "x": 150.0,
                        "y": -32.0
                    },
                    "vel": {
                        "x": 0.0,
                        "y": 2.0
                    }
                },
                {
                    "name": "",
                    "id": 5,
                    "type": 0,
                    "moveType": 0,
                    "lives": 1,
                    "hp": 20,
                    "radius": 12,
                    "shootType": 1,
                    "time": 10,
                    "spawnTime": 180,
                    "spellCount": 0,
                    "spellAmount": 0,
                    "isAlive": 0,
                    "isSpell": 0,
                    "isInvincible": 0,
                    "invincibleTime": 0,
                    "pos": {
                        "x": 180.0,
                        "y": -32.0
                    },
                    "vel": {
                        "x": 0.0,
                        "y": 2.0
                    }
                },
                {
                    "name": "",
                    "id": 6,
                    "type": 0,
                    "moveType": 0,
                    "lives": 1,
                    "hp": 20,
                    "radius": 12,
                    "shootType": 1,
                    "time": 10,
                    "spawnTime": 210,
                    "spellCount": 0,
                    "spellAmount": 0,
                    "isAlive": 0,
                    "isSpell": 0,
                    "isInvincible": 0,
                    "invincibleTime": 0,
                    "pos": {
                        "x": 210.0,
                        "y": -32.0
                    },
                    "vel": {
                        "x": 0.0,
                        "y": 2.0
                    }
                },
                {
                    "name": "",
                    "id": 7,
                    "type": 1,
                    "moveType": 0,
                    "lives": 1,
                    "hp": 20,
                    "radius": 12,
                    "shootType": 1,
                    "time": 0,
                    "spawnTime": 75,
                    "spellCount": 0,
                    "spellAmount": 0,
                    "isAlive": 0,
                    "isSpell": 0,
                    "isInvincible": 0,
                    "invincibleTime": 0,
                    "pos": {
                        "x": 480.0,
                        "y": -32.0
                    },
                    "vel": {
                        "x": 0.0,
                        "y": 2.0
                    }
                },
                {
                    "name": "",
                    "id": 8,
                    "type": 1,
                    "moveType": 0,
                    "lives": 1,
                    "hp": 20,
                    "radius": 12,
                    "shootType": 1,
                    "time": 0,
                    "spawnTime": 105,
                    "spellCount": 0,
                    "spellAmount": 0,
                    "isAlive": 0,
                    "isSpell": 0,
                    "isInvincible": 0,
                    "invincibleTime": 0,
                    "pos": {
                        "x": 450.0,
                        "y": -32.0
                    },
                    "vel": {
                        "x": 0.0,
                        "y": 2.0
                    }
                },
                {
                    "name": "",
                    "id": 9,
                    "type": 1,
                    "moveType": 0,
                    "lives": 1,
                    "hp": 20,
                    "radius": 12,
                    "shootType": 1,
                    "time": 0,
                    "spawnTime": 135,
                    "spellCount": 0,
                    "spellAmount": 0,
                    "isAlive": 0,
                    "isSpell": 0,
                    "isInvincible": 0,
                    "invincibleTime": 0,
                    "pos": {
                        "x": 420.0,
                        "y": -32.0
                    },
                    "vel": {
                        "x": 0.0,
                        "y": 2.0
                    }
                },
                {
                    "name": "",
                    "id": 10,
                    "type": 1,
                    "moveType": 0,
                    "lives": 1,
                    "hp": 20,
                    "radius": 12,
                    "shootType": 1,
                    "time": 0,
                    "spawnTime": 165,
                    "spellCount": 0,
                    "spellAmount": 0,
                    "isAlive": 0,
                    "isSpell": 0,
                    "isInvincible": 0,
                    "invincibleTime": 0,
                    "pos": {
                        "x": 390.0,
                        "y": -32.0
                    },
                    "vel": {
                        "x": 0.0,
                        "y": 2.0
                    }
                },
                {
                    "name": "",
                    "id": 11,
                    "type": 1,
                    "moveType": 0,
                    "lives": 1,
                    "hp": 20,
                    "radius": 12,
                    "shootType": 1,
                    "time": 0,
                    "spawnTime": 195,
                    "spellCount": 0,
                    "spellAmount": 0,
                    "isAlive": 0,
                    "isSpell": 0,
                    "isInvincible": 0,
                    "invincibleTime": 0,
                    "pos": {
                        "x": 360.0,
                        "y": -32.0
                    },
                    "vel": {
                        "x": 0.0,
                        "y": 2.0
                    }
                },
                {
                    "name": "",
                    "id": 12,
                    "type": 1,
                    "moveType": 0,
                    "lives": 1,
                    "hp": 80,
                    "radius": 12,
                    "shootType": 1,
                    "time": 0,
                    "spawnTime": 225,
                    "spellCount": 0,
                    "spellAmount": 0,
                    "isAlive": 0,
                    "isSpell": 0,
                    "isInvincible": 0,
                    "invincibleTime": 0,
                    "pos": {
                        "x": 330.0,
                        "y": -32.0
                    },
                    "vel": {
                        "x": 0.0,
                        "y": 2.0
                    }
                },
                {
                    "name": "",
                    "id": 13,
                    "type": 2,
                    "moveType": 2,
                    "lives": 1,
                    "hp": 80,
                    "radius": 12,
                    "shootType": 1,
                    "time": 0,
                    "spawnTime": 360,
                    "spellCount": 0,
                    "spellAmount": 0,
                    "isAlive": 0,
                    "isSpell": 0,
                    "isInvincible": 0,
                    "invincibleTime": 0,
                    "pos": {
                        "x": 120.0,
                        "y": -32.0
                    },
                    "vel": {
                        "x": 0.0,
                        "y": 2.0
                    }
                },
                {
                    "name": "",
                    "id": 14,
                    "type": 2,
                    "moveType": 2,
                    "lives": 1,
                    "hp": 80,
                    "radius": 12,
                    "shootType": 1,
                    "time": 0,
                    "spawnTime": 420,
                    "spellCount": 0,
                    "spellAmount": 0,
                    "isAlive": 0,
                    "isSpell": 0,
                    "isInvincible": 0,
                    "invincibleTime": 0,
                    "pos": {
                        "x": 180.0,
                        "y": -32.0
                    },
                    "vel": {
                        "x": 0.0,
                        "y": 2.0
                    }
                },
                {
                    "name": "",
                    "id": 15,
                    "type": 2,
                    "moveType": 2,
                    "lives": 1,
                    "hp": 80,
                    "radius": 12,
                    "shootType": 1,
                    "time": 0,
                    "spawnTime": 480,
                    "spellCount": 0,
                    "spellAmount": 0,
                    "isAlive": 0,
                    "isSpell": 0,
                    "isInvincible": 0,
                    "invincibleTime": 0,
                    "pos": {
                        "x": 40.0,
                        "y": -32.0
                    },
                    "vel": {
                        "x": 0.0,
                        "y": 2.0
                    }
                },
                {
                    "name": "",
                    "id": 16,
                    "type": 2,
                    "moveType": 2,
                    "lives": 1,
                    "hp": 50,
                    "radius": 12,
                    "shootType": 1,
                    "time": 0,
                    "spawnTime": 540,
                    "spellCount": 0,
                    "spellAmount": 0,
                    "isAlive": 0,
                    "isSpell": 0,
                    "isInvincible": 0,
                    "invincibleTime": 0,
                    "pos": {
                        "x": 300.0,
                        "y": -32.0
                    },
                    "vel": {
                        "x": 0.0,
                        "y": 2.0
                    }
                },
                {
                    "name": "",
                    "id": 17,
                    "type": 2,
                    "moveType": 2,
                    "lives": 1,
                    "hp": 50,
                    "radius": 12,
                    "shootType": 1,
                    "time": 0,
                    "spawnTime": 600,
                    "spellCount": 0,
                    "spellAmount": 0,
                    "isAlive": 0,
                    "isSpell": 0,
                    "isInvincible": 0,
                    "invincibleTime": 0,
                    "pos": {
                        "x": 360.0,
                        "y": -32.0
                    },
                    "vel": {
                        "x": 0.0,
                        "y": 2.0
                    }
                },
                {
                    "name": "",
                    "id": 18,
                    "type": 2,
                    "moveType": 2,
                    "lives": 1,
                    "hp": 50,
                    "radius": 12,
                    "shootType": 1,
                    "time": 0,
                    "spawnTime": 660,
                    "spellCount": 0,
                    "spellAmount": 0,
                    "isAlive": 0,
                    "isSpell": 0,
                    "isInvincible": 0,
                    "invincibleTime": 0,
                    "pos": {
                        "x": 220.0,
                        "y": -32.0
                    },
                    "vel": {
                        "x": 0.0,
                        "y": 2.0
                    }
                },
                {
                    "name": "",
                    "id": 19,
                    "type": 2,
                    "moveType": 2,
                    "lives": 1,
                    "hp": 50,
                    "radius": 12,
                    "shootType": 1,
                    "time": 0,
                    "spawnTime": 720,
                    "spellCount": 0,
                    "spellAmount": 0,
                    "isAlive": 0,
                    "isSpell": 0,
                    "isInvincible": 0,
                    "invincibleTime": 0,
                    "pos": {
                        "x": 180.0,
                        "y": -32.0
                    },
                    "vel": {
                        "x": 0.0,
                        "y": 2.0
                    }
                },
                {
                    "name": "",
                    "id": 20,
                    "type": 2,
                    "moveType": 2,
                    "lives": 1,
                    "hp": 50,
                    "radius": 12,
                    "shootType": 1,
                    "time": 0,
                    "spawnTime": 780,
                    "spellCount": 0,
                    "spellAmount": 0,
                    "isAlive": 0,
                    "isSpell": 0,
                    "isInvincible": 0,
                    "invincibleTime": 0,
                    "pos": {
                        "x": 340.0,
                        "y": -32.0
                    },
                    "vel": {
                        "x": 0.0,
                        "y": 2.0
                    }
                },
                {
                    "name": "",
                    "id": 21,
                    "type": 2,
                    "moveType": 2,
                    "lives": 1,
                    "hp": 50,
                    "radius": 12,
                    "shootType": 1,
                    "time": 0,
                    "spawnTime": 840,
                    "spellCount": 0,
                    "spellAmount": 0,
                    "isAlive": 0,
                    "isSpell": 0,
                    "isInvincible": 0,
                    "invincibleTime": 0,
                    "pos": {
                        "x": 100.0,
                        "y": -32.0
                    },
                    "vel": {
                        "x": 0.0,
                        "y": 2.0
                    }
                },
                {
                    "name": "",
                    "id": 22,
                    "type": 2,
                    "moveType": 2,
                    "lives": 1,
                    "hp": 50,
                    "radius": 12,
                    "shootType": 1,
                    "time": 0,
                    "spawnTime": 900,
                    "spellCount": 0,
                    "spellAmount": 0,
                    "isAlive": 0,
                    "isSpell": 0,
                    "isInvincible": 0,
                    "invincibleTime": 0,
                    "pos": {
                        "x": 60.0,
                        "y": -32.0
                    },
                    "vel": {
                        "x": 0.0,
                        "y": 2.0
                    }
                },
                {
                    "name": "",
                    "id": 23,
                    "type": 2,
                    "moveType": 2,
                    "lives": 1,
                    "hp": 50,
                    "radius": 12,
                    "shootType": 1,
                    "time": 0,
                    "spawnTime": 960,
                    "spellCount": 0,
                    "spellAmount": 0,
                    "isAlive": 0,
                    "isSpell": 0,
                    "isInvincible": 0,
                    "invincibleTime": 0,
                    "pos": {
                        "x": 320.0,
                        "y": -32.0
                    },
                    "vel": {
                        "x": 0.0,
                        "y": 2.0
                    }
                },
                {
                    "name": "",
                    "id": 24,
                    "type": 0,
                    "moveType": 4,
                    "lives": 1,
                    "hp": 150,
                    "radius": 12,
                    "shootType": 4,
                    "time": 0,
                    "spawnTime": 1500,
                    "spellCount": 0,
                    "spellAmount": 0,
                    "isAlive": 0,
                    "isSpell": 0,
                    "isInvincible": 0,
                    "invincibleTime": 0,
                    "pos": {
                        "x": 320.0,
                        "y": -32.0
                    },
                    "vel": {
                        "x": 0.0,
                        "y": 2.0
                    }
                },
                {
                    "name": "",
                    "id": 25,
                    "type": 0,
                    "moveType": 4,
                    "lives": 1,
                    "hp": 150,
                    "radius": 12,
                    "shootType": 4,
                    "time": 0,
                    "spawnTime": 1710,
                    "spellCount": 0,
                    "spellAmount": 0,
                    "isAlive": 0,
                    "isSpell": 0,
                    "isInvincible": 0,
                    "invincibleTime": 0,
                    "pos": {
                        "x": 120.0,
                        "y": -32.0
                    },
                    "vel": {
                        "x": 0.0,
                        "y": 2.0
                    }
                },
                {
                    "name": "",
                    "id": 26,
                    "type": 0,
                    "moveType": 4,
                    "lives": 1,
                    "hp": 150,
                    "radius": 12,
                    "shootType": 4,
                    "time": 0,
                    "spawnTime": 1920,
                    "spellCount": 0,
                    "spellAmount": 0,
                    "isAlive": 0,
                    "isSpell": 0,
                    "isInvincible": 0,
                    "invincibleTime": 0,
                    "pos": {
                        "x": 420.0,
                        "y": -32.0
                    },
                    "vel": {
                        "x": 0.0,
                        "y": 2.0
                    }
                },
                {
                    "name": "",
                    "id": 27,
                    "type": 0,
                    "moveType": 4,
                    "lives": 1,
                    "hp": 200,
                    "radius": 12,
                    "shootType": 4,
                    "time": 0,
                    "spawnTime": 2130,
                    "spellCount": 0,
                    "spellAmount": 0,
                    "isAlive": 0,
                    "isSpell": 0,
                    "isInvincible": 0,
                    "invincibleTime": 0,
                    "pos": {
                        "x": 120.0,
                        "y": -32.0
                    },
                    "vel": {
                        "x": 0.0,
                        "y": 2.0
                    }
                },
                {
                    "name": "",
                    "id": 28,
                    "type": 0,
                    "moveType": 4,
                    "lives": 1,
                    "hp": 200,
                    "radius": 12,
                    "shootType": 4,
                    "time": 0,
                    "spawnTime": 2340,
                    "spellCount": 0,
                    "spellAmount": 0,
                    "isAlive": 0,
                    "isSpell": 0,
                    "isInvincible": 0,
                    "invincibleTime": 0,
                    "pos": {
                        "x": 320.0,
                        "y": -32.0
                    },
                    "vel": {
                        "x": 0.0,
                        "y": 2.0
                    }
                },
                {
                    "name": "Boss",
                    "id": 102,
                    "type": 102,
                    "moveType": 4,
                    "lives": 5,
                    "hp": 1000,
                    "radius": 28,
                    "shootType": 7,
                    "time": 0,
                    "spawnTime": 2700,
                    "spellCount": 0,
                    "spellAmount": 5,
                    "isAlive": 0,
                    "isSpell": 0,
                    "isInvincible": 0,
                    "invincibleTime": 0,
                    "pos": {
                        "x": 320.0,
                        "y": -32.0
                    },
                    "vel": {
                        "x": 0.0,
                        "y": 2.0
                    }
                }
            ]
        }
    ]
}